dirtpy/__init__.py
dirtpy/ecs.py
dirtpy-0.1.0.dist-info/METADATA
dirtpy-0.1.0.dist-info/WHEEL
dirtpy-0.1.0.dist-info/top_level.txt
dirtpy-0.1.0.dist-info/RECORD
